telegram_sticker_utils-0.2.24.dist-info/METADATA
telegram_sticker_utils-0.2.24.dist-info/WHEEL
telegram_sticker_utils-0.2.24.dist-info/entry_points.txt
telegram_sticker_utils-0.2.24.dist-info/licenses/LICENSE
telegram_sticker_utils/__init__.py
telegram_sticker_utils/core/__init__.py
telegram_sticker_utils/core/_sort.py
telegram_sticker_utils/core/const.py
telegram_sticker_utils/core/rules.json
telegram_sticker_utils-0.2.24.dist-info/RECORD
