Metadata-Version: 2.1
Name: telegram-sticker-utils
Version: 0.2.24
Summary: easy and fast processing of telegram stickers
Keywords: telegram,sticker,image,video,processing,ffmpeg,pillow
Author-Email: sudoskys <coldlando@hotmail.com>
License: Apache-2.0
Project-URL: Repository, https://github.com/sudoskys/telegram-sticker-utils
Requires-Python: >=3.9
Requires-Dist: loguru>=0.7.2
Requires-Dist: Wand>=0.6.13
Requires-Dist: Pillow>=6.2.0
Requires-Dist: ffmpy>=0.3.2
Requires-Dist: emoji>=2.12.1
Requires-Dist: setuptools>=60.0.0
Requires-Dist: magika>=0.5.1
Requires-Dist: moviepy>=1.0.3
